LICENSE
README.md
setup.py
pysongtool/__init__.py
pysongtool/pysongtool.py
pysongtool.egg-info/PKG-INFO
pysongtool.egg-info/SOURCES.txt
pysongtool.egg-info/dependency_links.txt
pysongtool.egg-info/requires.txt
pysongtool.egg-info/top_level.txt
pysongtool/data/__init__.py
pysongtool/data/chords.py
pysongtool/data/fifths.py
pysongtool/data/intervals.py
pysongtool/data/progressions.py
pysongtool/data/scales.py
pysongtool/exceptions/UnknownChord.py
pysongtool/exceptions/UnknownScale.py
pysongtool/exceptions/WrongNote.py
pysongtool/exceptions/__init__.py
pysongtool/objects/CircularLinkedList.py
pysongtool/objects/__init__.py
tests/__init__.py
tests/test_pysongtool.py