Metadata-Version: 2.1
Name: pysongtool
Version: 0.11.6
Summary: A Python library that gives musical theory contend.
Home-page: https://github.com/MuriloRyan/pysongtool
Author: Murilo R.B Silva
License: MIT
Keywords: music theory scales chords intervals
Classifier: Intended Audience :: Developers
Classifier: Intended Audience :: Education
Classifier: License :: OSI Approved :: MIT License
Classifier: Programming Language :: Python :: 3
Classifier: Programming Language :: Python :: 3.7
Classifier: Programming Language :: Python :: 3.8
Classifier: Programming Language :: Python :: 3.9
Classifier: Programming Language :: Python :: 3.10
Classifier: Topic :: Software Development :: Libraries
Classifier: Topic :: Multimedia :: Sound/Audio :: Analysis
Requires-Python: >=3.7
License-File: LICENSE
Requires-Dist: iniconfig==2.0.0
Requires-Dist: packaging==24.2
Requires-Dist: pluggy==1.5.0
Requires-Dist: pytest==8.3.3
Requires-Dist: setuptools==75.6.0
